.coveragerc
.gitignore
AUTHORS.rst
CHANGELOG.rst
LICENSE.txt
README.md
justfile
setup.cfg
setup.py
docs/Makefile
docs/authors.rst
docs/changelog.rst
docs/conf.py
docs/index.rst
docs/license.rst
docs/_static/.gitignore
src/code_grader/__init__.py
src/code_grader/lexer.py
src/code_grader/pdfcreator.py
src/code_grader.egg-info/PKG-INFO
src/code_grader.egg-info/SOURCES.txt
src/code_grader.egg-info/dependency_links.txt
src/code_grader.egg-info/entry_points.txt
src/code_grader.egg-info/not-zip-safe
src/code_grader.egg-info/requires.txt
src/code_grader.egg-info/top_level.txt
tests/conftest.py