Metadata-Version: 2.1
Name: code-grader
Version: 0.1.7
Summary: Add a short description here!
Home-page: https://github.com/pyscaffold/pyscaffold/
Author: Stephan Seitz
Author-email: stephan.seitz@fau.de
License: mit
Project-URL: Documentation, https://pyscaffold.org/
Platform: any
Classifier: Development Status :: 4 - Beta
Classifier: Programming Language :: Python
Provides-Extra: testing
